Metadata-Version: 1.0
Name: sw-python-email-devino
Version: 0.0.2
Summary: Integration with email API of devinotele.com
Home-page: https://github.com/telminov/sw-python-email-devino
Author: Telminov Sergey
Author-email: UNKNOWN
License: The MIT License
Platform: UNKNOWN
